pynjector/__init__.py
pynjector/cell.py
pynjector/container.py
pynjector/dependa.py
pynjector/lifetime.py
pynjector/resolver.py
pynjector-0.1.3.dist-info/LICENSE
pynjector-0.1.3.dist-info/METADATA
pynjector-0.1.3.dist-info/WHEEL
pynjector-0.1.3.dist-info/top_level.txt
pynjector-0.1.3.dist-info/RECORD
