Metadata-Version: 2.2
Name: pynjector
Version: 0.1.3
Summary: A lightweight Dependency Injection (DI) container for Python
Author-email: "Sa(n)d" <oesand@github.com>
License: MIT
Project-URL: Homepage, https://github.com/oesand/pynjector
Project-URL: Repository, https://github.com/oesand/pynjector
Keywords: dependency injection,di,ioc,python
Classifier: Programming Language :: Python :: 3
Classifier: License :: OSI Approved :: MIT License
Classifier: Operating System :: OS Independent
Requires-Python: >=3.7
License-File: LICENSE
